phys_benchmark/__init__.py
phys_benchmark/analysis.py
phys_benchmark/ask_nodes.py
phys_benchmark/benchmark_12gpu_fun.py
phys_benchmark/benchmark_18gpu_fun.py
phys_benchmark/benchmark_1gpu_fun.py
phys_benchmark/benchmark_2gpu_fun.py
phys_benchmark/benchmark_3gpu_fun.py
phys_benchmark/benchmark_6gpu_fun.py
phys_benchmark/def_fun.py
phys_benchmark/def_fun_2nodes.py
phys_benchmark/def_fun_3nodes.py
phys_benchmark/def_fun_4nodes.py
phys_benchmark/delete.py
phys_benchmark/time.py
phys_benchmark-3.7.dist-info/METADATA
phys_benchmark-3.7.dist-info/WHEEL
phys_benchmark-3.7.dist-info/top_level.txt
phys_benchmark-3.7.dist-info/RECORD
