Metadata-Version: 2.1
Name: phys-benchmark
Version: 3.7
Summary: Benchamrking MD on PHYS MPU cluster
Home-page: https://github.com/louetadelie1/benchmark_phys.git/
Author: Adelie Louet
Author-email: adelie.louet@biophys.mpg.de
Classifier: Programming Language :: Python :: 3
Classifier: License :: OSI Approved :: MIT License
Classifier: Operating System :: OS Independent
Requires-Python: >=3.7
